brussel/__init__.py
brussel/brussel.py
brussel/exceptions.py
brussel/models.py
brussel/py.typed
brussel-1.0.0.dist-info/METADATA
brussel-1.0.0.dist-info/WHEEL
brussel-1.0.0.dist-info/licenses/LICENSE
brussel-1.0.0.dist-info/RECORD
